openrouter/__init__.py
openrouter/openrouter.py
openrouter/utils.py
xqcopenrouter-0.0.4.dist-info/licenses/LICENSE
xqcopenrouter-0.0.4.dist-info/METADATA
xqcopenrouter-0.0.4.dist-info/WHEEL
xqcopenrouter-0.0.4.dist-info/top_level.txt
xqcopenrouter-0.0.4.dist-info/RECORD
