Metadata-Version: 2.4
Name: XQCOpenRouter
Version: 0.0.4
Summary: 高效、易用的 OpenRouter API Python 客户端，支持同步与异步调用。
Author-email: Xiaoqiang <xiaoqiangclub@hotmail.com>
License: MIT
Classifier: Programming Language :: Python :: 3
Classifier: License :: OSI Approved :: MIT License
Classifier: Operating System :: OS Independent
Classifier: Intended Audience :: Developers
Classifier: Topic :: Software Development :: Libraries :: Python Modules
Requires-Python: >=3.10
License-File: LICENSE
Requires-Dist: httpx>=0.24.1
Dynamic: license-file
